Workbook

Sheet Hipótesis
A1: Inditex (ITX.MC) · Hipótesis del DCF
A2: Celdas amarillas con texto azul = hipótesis que puedes cambiar. Todo lo demás se recalcula solo.
A4: 1. Datos de mercado
A5: Precio de la acción (€) | B5: 53.24 | H5: Cierre 02/10/2026, Bolsa de Madrid (MarketScreener / Bolsamanía)
A6: Nº de acciones (millones) | B6: 3116.65 | H6: Capital social: 3.116.652.000 acciones (Inditex)
A7: Fecha de valoración | B7: 46298 | H7: Fecha del análisis
A8: Posición financiera neta (M€) | B8: 10958 | H8: Caja − deuda financiera a 31/01/2026, sin arrendamientos. Informe FY2025 Inditex
A10: 2. Coste de capital (WACC)
A11: Tipo libre de riesgo (bono España 10 años) | B11: 0.0415 | H11: Rentabilidad bono español 10a, 03/10/2026 (elEconomista / euribor.com.es)
A12: Beta | B12: 0.9 | H12: Beta 5 años mensual, Yahoo Finance (ITX.MC)
A13: Prima de riesgo del mercado (ERP) | B13: 0.045 | H13: Damodaran: ERP mercado maduro 4,17% (jul. 2026) + pequeño ajuste por España
A14: Coste del capital propio (Ke) = Rf + β × ERP | B14: =B11+B12*B13 -> 0.082
A15: Peso de la deuda financiera | B15: 0 | H15: Inditex no tiene deuda financiera neta (tiene caja neta) → WACC = Ke
A16: Coste de la deuda después de impuestos | B16: 0.03 | H16: Solo influye si cambias el peso de la deuda
A17: WACC | B17: =B14*(1-B15)+B16*B15 -> 0.082
A18: Crecimiento a perpetuidad (g) | B18: 0.025 | H18: ≈ inflación a largo plazo + algo de crecimiento real. Debe ser < WACC
A20: 3. Hipótesis operativas
A21: Ejercicio (cierra el 31 de enero del año siguiente) | C21: 2026e | D21: 2027e | E21: 2028e | F21: 2029e | G21: 2030e | H21: Por qué
A22: Crecimiento de ventas | C22: 0.07 | D22: 0.065 | E22: 0.06 | F22: 0.055 | G22: 0.05 | H22: 1S 2026: +7,6% (+9,2% a tipo constante). Se va frenando hacia el largo plazo.
A23: Margen EBIT | C23: 0.203 | D23: 0.205 | E23: 0.206 | F23: 0.207 | G23: 0.208 | H23: FY2025: 20,1%. Guía: margen bruto estable ±50 pb. Mejora lenta por apalancamiento operativo.
A24: Amortizaciones (% ventas) | C24: 0.082 | D24: 0.082 | E24: 0.082 | F24: 0.082 | G24: 0.082 | H24: FY2025: 3.270 M€ = 8,2% de ventas (incluye amortización de tiendas alquiladas, NIIF 16).
A25: Capex (% ventas) | C25: 0.054 | D25: 0.055 | E25: 0.055 | F25: 0.055 | G25: 0.055 | H25: Guía 2026: capex ordinario ≈ 2.300 M€ (≈5,4% de ventas).
A26: Pagos por arrendamientos (% ventas) | C26: 0.046 | D26: 0.046 | E26: 0.046 | F26: 0.046 | G26: 0.046 | H26: FY2025: 1.834 M€ = 4,6% de ventas. Se restan porque son un coste real de caja.
A27: Inversión en circulante (% del aumento de ventas) | C27: 0.05 | D27: 0.05 | E27: 0.05 | F27: 0.05 | G27: 0.05 | H27: Hipótesis prudente. Inditex suele tener circulante negativo, pero en 2025 consumió 803 M€.
A28: Tipo impositivo | C28: 0.225 | D28: 0.225 | E28: 0.225 | F28: 0.225 | G28: 0.225 | H28: FY2025: (BAI 8.020 − beneficio 6.220) / 8.020 ≈ 22,4%.
A31: Datos reales del ejercicio 2025 (punto de partida)
A32: Ventas FY2025 (M€) | B32: 39864 | H32: Informe FY2025 Inditex
A33: EBIT FY2025 (M€) | B33: 7997 | H33: Informe FY2025 Inditex
A34: Amortizaciones FY2025 (M€) | B34: 3270 | H34: Informe FY2025 Inditex
A35: Capex FY2025 (M€) | B35: 2712 | H35: Informe FY2025 Inditex (incluye inversión extraordinaria en logística)
A36: Pagos por arrendamientos FY2025 (M€) | B36: 1834 | H36: Informe FY2025 Inditex
A38: Leyenda:
A39: Azul sobre amarillo = hipótesis editable
A40: Negro = fórmula (no tocar)
A41: Verde = dato traído de otra hoja

Sheet DCF
A1: Inditex (ITX.MC) · Descuento de flujos de caja (M€)
A3: Ejercicio fiscal | B3: 2022 | C3: 2023 | D3: 2024 | E3: 2025 | F3: 2026e | G3: 2027e | H3: 2028e | I3: 2029e | J3: 2030e
B4: ← Histórico (real) | F4: Proyección →
A5: Ventas | B5: 32569 | C5: 35947 | D5: 38632 | E5: =Hipótesis!B32 -> 39864 | F5: =E5*(1+F6) -> 42654.48 | G5: =F5*(1+G6) -> 45427.021 | H5: =G5*(1+H6) -> 48152.642 | I5: =H5*(1+I6) -> 50801.038 | J5: =I5*(1+J6) -> 53341.09
A6: Crecimiento | C6: =C5/B5-1 -> 0.10371826 | D6: =D5/C5-1 -> 0.074693298 | E6: =E5/D5-1 -> 0.031890661 | F6: =Hipótesis!C22 -> 0.07 | G6: =Hipótesis!D22 -> 0.065 | H6: =Hipótesis!E22 -> 0.06 | I6: =Hipótesis!F22 -> 0.055 | J6: =Hipótesis!G22 -> 0.05
A7: EBIT (resultado de explotación) | B7: =B5*B8 -> 5894.989 | C7: =C5*C8 -> 6901.824 | D7: =D5*D8 -> 7687.768 | E7: =Hipótesis!B33 -> 7997 | F7: =F5*F8 -> 8658.8594 | G7: =G5*G8 -> 9312.5393 | H7: =H5*H8 -> 9919.4443 | I7: =I5*I8 -> 10515.815 | J7: =J5*J8 -> 11094.947
A8: Margen EBIT | B8: 0.181 | C8: 0.192 | D8: 0.199 | E8: =E7/E5 -> 0.20060706 | F8: =Hipótesis!C23 -> 0.203 | G8: =Hipótesis!D23 -> 0.205 | H8: =Hipótesis!E23 -> 0.206 | I8: =Hipótesis!F23 -> 0.207 | J8: =Hipótesis!G23 -> 0.208
A9: (−) Impuestos sobre el EBIT | F9: =-F7*Hipótesis!C28 -> -1948.2434 | G9: =-G7*Hipótesis!D28 -> -2095.3214 | H9: =-H7*Hipótesis!E28 -> -2231.875 | I9: =-I7*Hipótesis!F28 -> -2366.0583 | J9: =-J7*Hipótesis!G28 -> -2496.363
A10: NOPAT (EBIT después de impuestos) | F10: =F7+F9 -> 6710.6161 | G10: =G7+G9 -> 7217.218 | H10: =H7+H9 -> 7687.5694 | I10: =I7+I9 -> 8149.7565 | J10: =J7+J9 -> 8598.5837
A11: (+) Amortizaciones | E11: =Hipótesis!B34 -> 3270 | F11: =F5*Hipótesis!C24 -> 3497.6674 | G11: =G5*Hipótesis!D24 -> 3725.0157 | H11: =H5*Hipótesis!E24 -> 3948.5167 | I11: =I5*Hipótesis!F24 -> 4165.6851 | J11: =J5*Hipótesis!G24 -> 4373.9694
A12: (−) Capex (inversiones) | E12: =-Hipótesis!B35 -> -2712 | F12: =-F5*Hipótesis!C25 -> -2303.3419 | G12: =-G5*Hipótesis!D25 -> -2498.4862 | H12: =-H5*Hipótesis!E25 -> -2648.3953 | I12: =-I5*Hipótesis!F25 -> -2794.0571 | J12: =-J5*Hipótesis!G25 -> -2933.7599
A13: (−) Pagos por arrendamientos | E13: =-Hipótesis!B36 -> -1834 | F13: =-F5*Hipótesis!C26 -> -1962.1061 | G13: =-G5*Hipótesis!D26 -> -2089.643 | H13: =-H5*Hipótesis!E26 -> -2215.0216 | I13: =-I5*Hipótesis!F26 -> -2336.8477 | J13: =-J5*Hipótesis!G26 -> -2453.6901
A14: (−) Inversión en circulante | F14: =-(F5-E5)*Hipótesis!C27 -> -139.524 | G14: =-(G5-F5)*Hipótesis!D27 -> -138.62706 | H14: =-(H5-G5)*Hipótesis!E27 -> -136.28106 | I14: =-(I5-H5)*Hipótesis!F27 -> -132.41977 | J14: =-(J5-I5)*Hipótesis!G27 -> -127.00259
A15: Flujo de caja libre (FCF) | F15: =F10+F11+F12+F13+F14 -> 5803.3114 | G15: =G10+G11+G12+G13+G14 -> 6215.4775 | H15: =H10+H11+H12+H13+H14 -> 6636.3881 | I15: =I10+I11+I12+I13+I14 -> 7052.117 | J15: =J10+J11+J12+J13+J14 -> 7458.1004
A17: Años desde la fecha de valoración | F17: =(DATE(2027,1,31)-Hipótesis!$B$7)/365 -> 0.32876712 | G17: =(DATE(2028,1,31)-Hipótesis!$B$7)/365 -> 1.3287671 | H17: =(DATE(2029,1,31)-Hipótesis!$B$7)/365 -> 2.3315068 | I17: =(DATE(2030,1,31)-Hipótesis!$B$7)/365 -> 3.3315068 | J17: =(DATE(2031,1,31)-Hipótesis!$B$7)/365 -> 4.3315068
A18: Factor de descuento | F18: =1/(1+Hipótesis!$B$17)^F17 -> 0.97442227 | G18: =1/(1+Hipótesis!$B$17)^G17 -> 0.90057511 | H18: =1/(1+Hipótesis!$B$17)^H17 -> 0.83214481 | I18: =1/(1+Hipótesis!$B$17)^I17 -> 0.76908023 | J18: =1/(1+Hipótesis!$B$17)^J17 -> 0.71079504
A19: Valor actual del FCF | F19: =F15*F18 -> 5654.8759 | G19: =G15*G18 -> 5597.5044 | H19: =H15*H18 -> 5522.4359 | I19: =I15*I18 -> 5423.6438 | J19: =J15*J18 -> 5301.1807
A22: Valoración
A23: Suma del valor actual de los FCF 2026e-2030e | B23: =SUM(F19:J19) -> 27499.641 | D23: Comprobaciones
A24: FCF del último año proyectado × (1 + g) | B24: =J15*(1+Hipótesis!B18) -> 7644.5529 | D24: Peso del valor terminal en el EV | H24: =B26/B27 -> 0.77611241
A25: Valor terminal en 2030 = FCF₂₀₃₁ / (WACC − g) | B25: =B24/(Hipótesis!B17-Hipótesis!B18) -> 134114.96 | D25: EV / EBIT 2026e implícito | H25: =B27/F7 -> 14.185227
A26: Valor actual del valor terminal | B26: =B25*J18 -> 95328.25 | D26: PER 2026e implícito (aprox.) | H26: =B29/((F7+Hipótesis!B8*0.02)*(1-Hipótesis!C28)) -> 19.444309
A27: Valor de empresa (EV) | B27: =B23+B26 -> 122827.89 | D27: Precio que paga el mercado: EV / EBIT 2026e | H27: =(Hipótesis!B5*Hipótesis!B6-Hipótesis!B8)/F7 -> 17.897559
A28: (+) Posición financiera neta (caja neta) | B28: =Hipótesis!B8 -> 10958 | D28: WACC usado | H28: =Hipótesis!B17 -> 0.082
A29: Valor de los fondos propios | B29: =B27+B28 -> 133785.89 | D29: g usado | H29: =Hipótesis!B18 -> 0.025
A30: Nº de acciones (millones) | B30: =Hipótesis!B6 -> 3116.65
A31: VALOR POR ACCIÓN (€) | B31: =B29/B30 -> 42.926184
A32: Precio actual (€) | B32: =Hipótesis!B5 -> 53.24
A33: Potencial de revalorización (+) / caída (−) | B33: =B31/B32-1 -> -0.19372307
A36: Cómo se calcula el FCF
A37: • FCF = EBIT × (1 − impuestos) + amortizaciones − capex − pagos por arrendamientos − inversión en circulante.
A38: • Los alquileres de tiendas se restan como pago de caja; por eso NO se resta la deuda por arrendamientos (NIIF 16) del valor de empresa.
A39: • Al valor de empresa solo se le suma la caja neta financiera (10.958 M€), no la 'deuda total' de Yahoo.
A40: • Simplificación: el FCF de 2026e se descuenta entero aunque parte del ejercicio ya ha pasado, y la caja es la de 31/01/2026.

Sheet Sensibilidad
A1: Valor por acción (€) según WACC y crecimiento a perpetuidad (g)
B3: WACC ↓ / g → | C3: 0.015 | D3: 0.02 | E3: 0.025 | F3: 0.03 | G3: 0.035
B4: 0.07 | C4: =(SUMPRODUCT(DCF!$F$15:$J$15/(1+$B4)^DCF!$F$17:$J$17)+DCF!$J$15*(1+C$3)/($B4-C$3)/(1+$B4)^DCF!$J$17+Hipótesis!$B$8)/Hipótesis!$B$6 -> 45.51296 | D4: =(SUMPRODUCT(DCF!$F$15:$J$15/(1+$B4)^DCF!$F$17:$J$17)+DCF!$J$15*(1+D$3)/($B4-D$3)/(1+$B4)^DCF!$J$17+Hipótesis!$B$8)/Hipótesis!$B$6 -> 48.985804 | E4: =(SUMPRODUCT(DCF!$F$15:$J$15/(1+$B4)^DCF!$F$17:$J$17)+DCF!$J$15*(1+E$3)/($B4-E$3)/(1+$B4)^DCF!$J$17+Hipótesis!$B$8)/Hipótesis!$B$6 -> 53.230391 | F4: =(SUMPRODUCT(DCF!$F$15:$J$15/(1+$B4)^DCF!$F$17:$J$17)+DCF!$J$15*(1+F$3)/($B4-F$3)/(1+$B4)^DCF!$J$17+Hipótesis!$B$8)/Hipótesis!$B$6 -> 58.536124 | G4: =(SUMPRODUCT(DCF!$F$15:$J$15/(1+$B4)^DCF!$F$17:$J$17)+DCF!$J$15*(1+G$3)/($B4-G$3)/(1+$B4)^DCF!$J$17+Hipótesis!$B$8)/Hipótesis!$B$6 -> 65.357782
B5: 0.075 | C5: =(SUMPRODUCT(DCF!$F$15:$J$15/(1+$B5)^DCF!$F$17:$J$17)+DCF!$J$15*(1+C$3)/($B5-C$3)/(1+$B5)^DCF!$J$17+Hipótesis!$B$8)/Hipótesis!$B$6 -> 42.066766 | D5: =(SUMPRODUCT(DCF!$F$15:$J$15/(1+$B5)^DCF!$F$17:$J$17)+DCF!$J$15*(1+D$3)/($B5-D$3)/(1+$B5)^DCF!$J$17+Hipótesis!$B$8)/Hipótesis!$B$6 -> 44.916201 | E5: =(SUMPRODUCT(DCF!$F$15:$J$15/(1+$B5)^DCF!$F$17:$J$17)+DCF!$J$15*(1+E$3)/($B5-E$3)/(1+$B5)^DCF!$J$17+Hipótesis!$B$8)/Hipótesis!$B$6 -> 48.335523 | F5: =(SUMPRODUCT(DCF!$F$15:$J$15/(1+$B5)^DCF!$F$17:$J$17)+DCF!$J$15*(1+F$3)/($B5-F$3)/(1+$B5)^DCF!$J$17+Hipótesis!$B$8)/Hipótesis!$B$6 -> 52.514694 | G5: =(SUMPRODUCT(DCF!$F$15:$J$15/(1+$B5)^DCF!$F$17:$J$17)+DCF!$J$15*(1+G$3)/($B5-G$3)/(1+$B5)^DCF!$J$17+Hipótesis!$B$8)/Hipótesis!$B$6 -> 57.738658
B6: 0.08 | C6: =(SUMPRODUCT(DCF!$F$15:$J$15/(1+$B6)^DCF!$F$17:$J$17)+DCF!$J$15*(1+C$3)/($B6-C$3)/(1+$B6)^DCF!$J$17+Hipótesis!$B$8)/Hipótesis!$B$6 -> 39.151316 | D6: =(SUMPRODUCT(DCF!$F$15:$J$15/(1+$B6)^DCF!$F$17:$J$17)+DCF!$J$15*(1+D$3)/($B6-D$3)/(1+$B6)^DCF!$J$17+Hipótesis!$B$8)/Hipótesis!$B$6 -> 41.52539 | E6: =(SUMPRODUCT(DCF!$F$15:$J$15/(1+$B6)^DCF!$F$17:$J$17)+DCF!$J$15*(1+E$3)/($B6-E$3)/(1+$B6)^DCF!$J$17+Hipótesis!$B$8)/Hipótesis!$B$6 -> 44.331113 | F6: =(SUMPRODUCT(DCF!$F$15:$J$15/(1+$B6)^DCF!$F$17:$J$17)+DCF!$J$15*(1+F$3)/($B6-F$3)/(1+$B6)^DCF!$J$17+Hipótesis!$B$8)/Hipótesis!$B$6 -> 47.69798 | G6: =(SUMPRODUCT(DCF!$F$15:$J$15/(1+$B6)^DCF!$F$17:$J$17)+DCF!$J$15*(1+G$3)/($B6-G$3)/(1+$B6)^DCF!$J$17+Hipótesis!$B$8)/Hipótesis!$B$6 -> 51.81304
B7: 0.085 | C7: =(SUMPRODUCT(DCF!$F$15:$J$15/(1+$B7)^DCF!$F$17:$J$17)+DCF!$J$15*(1+C$3)/($B7-C$3)/(1+$B7)^DCF!$J$17+Hipótesis!$B$8)/Hipótesis!$B$6 -> 36.652867 | D7: =(SUMPRODUCT(DCF!$F$15:$J$15/(1+$B7)^DCF!$F$17:$J$17)+DCF!$J$15*(1+D$3)/($B7-D$3)/(1+$B7)^DCF!$J$17+Hipótesis!$B$8)/Hipótesis!$B$6 -> 38.656713 | E7: =(SUMPRODUCT(DCF!$F$15:$J$15/(1+$B7)^DCF!$F$17:$J$17)+DCF!$J$15*(1+E$3)/($B7-E$3)/(1+$B7)^DCF!$J$17+Hipótesis!$B$8)/Hipótesis!$B$6 -> 40.994534 | F7: =(SUMPRODUCT(DCF!$F$15:$J$15/(1+$B7)^DCF!$F$17:$J$17)+DCF!$J$15*(1+F$3)/($B7-F$3)/(1+$B7)^DCF!$J$17+Hipótesis!$B$8)/Hipótesis!$B$6 -> 43.757413 | G7: =(SUMPRODUCT(DCF!$F$15:$J$15/(1+$B7)^DCF!$F$17:$J$17)+DCF!$J$15*(1+G$3)/($B7-G$3)/(1+$B7)^DCF!$J$17+Hipótesis!$B$8)/Hipótesis!$B$6 -> 47.072867
B8: 0.09 | C8: =(SUMPRODUCT(DCF!$F$15:$J$15/(1+$B8)^DCF!$F$17:$J$17)+DCF!$J$15*(1+C$3)/($B8-C$3)/(1+$B8)^DCF!$J$17+Hipótesis!$B$8)/Hipótesis!$B$6 -> 34.488006 | D8: =(SUMPRODUCT(DCF!$F$15:$J$15/(1+$B8)^DCF!$F$17:$J$17)+DCF!$J$15*(1+D$3)/($B8-D$3)/(1+$B8)^DCF!$J$17+Hipótesis!$B$8)/Hipótesis!$B$6 -> 36.198274 | E8: =(SUMPRODUCT(DCF!$F$15:$J$15/(1+$B8)^DCF!$F$17:$J$17)+DCF!$J$15*(1+E$3)/($B8-E$3)/(1+$B8)^DCF!$J$17+Hipótesis!$B$8)/Hipótesis!$B$6 -> 38.171661 | F8: =(SUMPRODUCT(DCF!$F$15:$J$15/(1+$B8)^DCF!$F$17:$J$17)+DCF!$J$15*(1+F$3)/($B8-F$3)/(1+$B8)^DCF!$J$17+Hipótesis!$B$8)/Hipótesis!$B$6 -> 40.473945 | G8: =(SUMPRODUCT(DCF!$F$15:$J$15/(1+$B8)^DCF!$F$17:$J$17)+DCF!$J$15*(1+G$3)/($B8-G$3)/(1+$B8)^DCF!$J$17+Hipótesis!$B$8)/Hipótesis!$B$6 -> 43.194827
B9: 0.095 | C9: =(SUMPRODUCT(DCF!$F$15:$J$15/(1+$B9)^DCF!$F$17:$J$17)+DCF!$J$15*(1+C$3)/($B9-C$3)/(1+$B9)^DCF!$J$17+Hipótesis!$B$8)/Hipótesis!$B$6 -> 32.594175 | D9: =(SUMPRODUCT(DCF!$F$15:$J$15/(1+$B9)^DCF!$F$17:$J$17)+DCF!$J$15*(1+D$3)/($B9-D$3)/(1+$B9)^DCF!$J$17+Hipótesis!$B$8)/Hipótesis!$B$6 -> 34.068015 | E9: =(SUMPRODUCT(DCF!$F$15:$J$15/(1+$B9)^DCF!$F$17:$J$17)+DCF!$J$15*(1+E$3)/($B9-E$3)/(1+$B9)^DCF!$J$17+Hipótesis!$B$8)/Hipótesis!$B$6 -> 35.752405 | F9: =(SUMPRODUCT(DCF!$F$15:$J$15/(1+$B9)^DCF!$F$17:$J$17)+DCF!$J$15*(1+F$3)/($B9-F$3)/(1+$B9)^DCF!$J$17+Hipótesis!$B$8)/Hipótesis!$B$6 -> 37.695931 | G9: =(SUMPRODUCT(DCF!$F$15:$J$15/(1+$B9)^DCF!$F$17:$J$17)+DCF!$J$15*(1+G$3)/($B9-G$3)/(1+$B9)^DCF!$J$17+Hipótesis!$B$8)/Hipótesis!$B$6 -> 39.963378
B11: Precio actual: | C11: =Hipótesis!B5 -> 53.24
B12: Caso base: | C12: =DCF!B31 -> 42.926184
B14: Cómo leerla: cada celda es el valor por acción si cambias solo el WACC (fila) y g (columna). Verde = por encima del precio actual; rojo = por debajo.

Sheet Múltiplos
A1: Inditex (ITX.MC) · Valoración por múltiplos de comparables
A2: Estimaciones de consenso del ejercicio en curso (MarketScreener, 02/10/2026). Cada empresa en su moneda y en millones: los múltiplos no dependen de la moneda.
A4: Empresa | B4: Moneda | C4: Capitalización | D4: Valor empresa (EV) | E4: EBIT | F4: Beneficio neto | G4: EV / EBIT | H4: PER | I4: Ejercicio | J4: Comentario
A5: H&M | B5: SEK | C5: 254222 | D5: 308232 | E5: 19234 | F5: 12698 | G5: =D5/E5 -> 16.025372 | H5: =C5/F5 -> 20.020633 | I5: nov-2026e | J5: Competidor más directo. Crece poco y con márgenes muy inferiores.
A6: Fast Retailing (Uniqlo) | B6: JPY | C6: 20841322 | D6: 19809562 | E6: 733476 | F6: 512531 | G6: =D6/E6 -> 27.007785 | H6: =C6/F6 -> 40.663534 | I6: ago-2026e | J6: El otro 'ganador' global del sector; cotiza con prima.
A7: Next plc | B7: GBP | C7: 16729 | D7: 18447 | E7: 1337 | F7: 943.1 | G7: =D7/E7 -> 13.797307 | H7: =C7/F7 -> 17.73831 | I7: ene-2027e | J7: Moda británica, fuerte en online.
A8: Associated British Foods (Primark) | B8: GBP | C8: 12767 | D8: 15605 | E8: 1505 | F8: 1013 | G8: =D8/E8 -> 10.368771 | H8: =C8/F8 -> 12.603159 | I8: sep-2026e | J8: Incluye negocio de alimentación: cotiza con descuento.
A9: Mediana de comparables | G9: =MEDIAN(G5:G8) -> 14.91134 | H9: =MEDIAN(H5:H8) -> 18.879471
A10: Mínimo | G10: =MIN(G5:G8) -> 10.368771 | H10: =MIN(H5:H8) -> 12.603159
A11: Máximo | G11: =MAX(G5:G8) -> 27.007785 | H11: =MAX(H5:H8) -> 40.663534
A13: Inditex (precio actual) | B13: EUR | C13: =Hipótesis!B5*Hipótesis!B6 -> 165930.45 | D13: =C13-Hipótesis!B8 -> 154972.45 | E13: 8667 | F13: 6735 | G13: =D13/E13 -> 17.880748 | H13: =C13/F13 -> 24.637037 | I13: ene-2027e | J13: EBIT y beneficio: consenso MarketScreener. EV con la caja neta de 31/01/2026.
A14: Prima de Inditex frente a la mediana | G14: =G13/G9-1 -> 0.19913763 | H14: =H13/H9-1 -> 0.30496435
A17: Valor implícito de Inditex (€/acción) | B17: Mínimo | C17: Mediana | D17: Máximo
A18: Por EV / EBIT | B18: =(G10*$E$13+Hipótesis!$B$8)/Hipótesis!$B$6 -> 32.350163 | C18: =(G9*$E$13+Hipótesis!$B$8)/Hipótesis!$B$6 -> 44.982459 | D18: =(G11*$E$13+Hipótesis!$B$8)/Hipótesis!$B$6 -> 78.621106
A19: Por PER | B19: =H10*$F$13/Hipótesis!$B$6 -> 27.2351 | C19: =H9*$F$13/Hipótesis!$B$6 -> 40.798049 | D19: =H11*$F$13/Hipótesis!$B$6 -> 87.872846
A20: Media de ambos métodos (mediana) | C20: =AVERAGE(C18:C19) -> 42.890254
A23: Precio objetivo combinado | B23: Peso | C23: €/acción
A24: DCF (caso base) | B24: 0.5 | C24: =DCF!B31 -> 42.926184
A25: Múltiplos (mediana) | B25: =1-B24 -> 0.5 | C25: =C20 -> 42.890254
A26: PRECIO OBJETIVO | C26: =SUMPRODUCT(B24:B25,C24:C25) -> 42.908219
A27: Precio actual | C27: =Hipótesis!B5 -> 53.24
A28: Potencial | C28: =C26/C27-1 -> -0.1940605
A29: Recomendación | C29: =IF(C28>0.15,"COMPRAR",IF(C28<-0.15,"VENDER","MANTENER")) -> VENDER | D29: Regla: potencial > +15% → Comprar · entre −15% y +15% → Mantener · < −15% → Vender
A31: Notas
A32: • Se usan EV/EBIT y PER porque EV/EBITDA se distorsiona con la NIIF 16 (cada empresa trata los alquileres de forma distinta).
A33: • Inditex merece cotizar con prima frente a H&M, Next y ABF por sus márgenes (EBIT ≈ 20% vs. 8-18%) y su caja neta; Fast Retailing es el único comparable de calidad similar.
A34: • Fuente: MarketScreener, páginas de valoración de cada empresa, consultadas el 03/10/2026.
A37: Campo de fútbol (rangos de valor, €/acción) | B37: Mínimo | C37: Máximo | D37: Cómo se obtiene
A38: Cotización últimas 52 semanas | B38: 46.07 | C38: 59.42 | D38: Mínimo y máximo de 52 semanas (estrategiasdeinversion.com, 02/10/2026)
A39: DCF (WACC 7,5-8,5%, g 2-3%) | B39: =MIN(Sensibilidad!D5:F7) -> 38.656713 | C39: =MAX(Sensibilidad!D5:F7) -> 52.514694 | D39: Zona central de la tabla de sensibilidad
A40: Múltiplos EV/EBIT (percentil 25-75) | B40: =(QUARTILE(G5:G8,1)*$E$13+Hipótesis!$B$8)/Hipótesis!$B$6 -> 39.5009 | C40: =(QUARTILE(G5:G8,3)*$E$13+Hipótesis!$B$8)/Hipótesis!$B$6 -> 55.715605 | D40: EV/EBIT de comparables × EBIT 2026e + caja neta
A41: Múltiplos PER (percentil 25-75) | B41: =QUARTILE(H5:H8,1)*$F$13/Hipótesis!$B$6 -> 35.557796 | C41: =QUARTILE(H5:H8,3)*$F$13/Hipótesis!$B$6 -> 54.416264 | D41: PER de comparables × beneficio 2026e
